ut_ptc/__init__.py
ut_ptc/__version__.py
ut_ptc/ptc.py
ut_ptc/py.typed
ut_ptc-2.0.0.20251020.dist-info/licenses/LICENSE.txt
ut_ptc-2.0.0.20251020.dist-info/METADATA
ut_ptc-2.0.0.20251020.dist-info/WHEEL
ut_ptc-2.0.0.20251020.dist-info/top_level.txt
ut_ptc-2.0.0.20251020.dist-info/RECORD
